zeversolar/__init__.py
zeversolar/exceptions.py
zeversolar-0.3.1.dist-info/LICENSE.md
zeversolar-0.3.1.dist-info/WHEEL
zeversolar-0.3.1.dist-info/METADATA
zeversolar-0.3.1.dist-info/RECORD
